odoo/addons/sale_order_general_discount/README.rst
odoo/addons/sale_order_general_discount/__init__.py
odoo/addons/sale_order_general_discount/__manifest__.py
odoo/addons/sale_order_general_discount/i18n/ca.po
odoo/addons/sale_order_general_discount/i18n/de.po
odoo/addons/sale_order_general_discount/i18n/es.po
odoo/addons/sale_order_general_discount/i18n/it.po
odoo/addons/sale_order_general_discount/i18n/sale_order_general_discount.pot
odoo/addons/sale_order_general_discount/i18n/zh_CN.po
odoo/addons/sale_order_general_discount/models/__init__.py
odoo/addons/sale_order_general_discount/models/res_partner.py
odoo/addons/sale_order_general_discount/models/sale.py
odoo/addons/sale_order_general_discount/readme/CONTRIBUTORS.rst
odoo/addons/sale_order_general_discount/readme/DESCRIPTION.rst
odoo/addons/sale_order_general_discount/readme/INSTALL.rst
odoo/addons/sale_order_general_discount/readme/USAGE.rst
odoo/addons/sale_order_general_discount/static/description/icon.png
odoo/addons/sale_order_general_discount/static/description/index.html
odoo/addons/sale_order_general_discount/tests/__init__.py
odoo/addons/sale_order_general_discount/tests/test_sale_order_general_discount.py
odoo/addons/sale_order_general_discount/views/res_partner_view.xml
odoo/addons/sale_order_general_discount/views/sale_order_view.xml
odoo12_addon_sale_order_general_discount-12.0.1.1.0.dist-info/METADATA
odoo12_addon_sale_order_general_discount-12.0.1.1.0.dist-info/WHEEL
odoo12_addon_sale_order_general_discount-12.0.1.1.0.dist-info/top_level.txt
odoo12_addon_sale_order_general_discount-12.0.1.1.0.dist-info/RECORD
